oaaclient/__init__.py
oaaclient/client.py
oaaclient/structures.py
oaaclient/templates.py
oaaclient/utils.py
oaaclient-1.1.15.dist-info/licenses/LICENSE
oaaclient-1.1.15.dist-info/METADATA
oaaclient-1.1.15.dist-info/WHEEL
oaaclient-1.1.15.dist-info/entry_points.txt
oaaclient-1.1.15.dist-info/top_level.txt
oaaclient-1.1.15.dist-info/RECORD
