Metadata-Version: 2.4
Name: oaaclient
Version: 1.1.15
Summary: Veza Open Authorization API (OAA) SDK
Author-email: "Veza Technologies Inc." <oaa_dev@veza.com>
License: MIT
Project-URL: homepage, https://github.com/veza/oaaclient-py
Project-URL: repository, https://github.com/veza/oaaclient-py
Requires-Python: >=3.8
License-File: LICENSE
Requires-Dist: requests<3,>=2.27
Provides-Extra: test
Requires-Dist: pytest; extra == "test"
Requires-Dist: pytest-cov; extra == "test"
Requires-Dist: pytest-timeout; extra == "test"
Requires-Dist: flake8; extra == "test"
Dynamic: license-file
